AUTHORS
LICENSE
MANIFEST.in
NEWS
README
setup.py
src/HTSQL_MYSQL.egg-info/PKG-INFO
src/HTSQL_MYSQL.egg-info/SOURCES.txt
src/HTSQL_MYSQL.egg-info/dependency_links.txt
src/HTSQL_MYSQL.egg-info/entry_points.txt
src/HTSQL_MYSQL.egg-info/not-zip-safe
src/HTSQL_MYSQL.egg-info/requires.txt
src/HTSQL_MYSQL.egg-info/top_level.txt
src/htsql_mysql/__init__.py
src/htsql_mysql/core/__init__.py
src/htsql_mysql/core/connect.py
src/htsql_mysql/core/introspect.py
src/htsql_mysql/core/split_sql.py
src/htsql_mysql/core/tr/__init__.py
src/htsql_mysql/core/tr/compile.py
src/htsql_mysql/core/tr/dump.py
src/htsql_mysql/core/tr/reduce.py
src/htsql_mysql/core/tr/signature.py