Metadata-Version: 1.0
Name: HTSQL-MYSQL
Version: 2.3.1
Summary: A Database Query Language (MySQL backend)
Home-page: http://htsql.org/
Author: Clark C. Evans and Kirill Simonov; Prometheus Research, LLC
Author-email: cce@clarkevans.com, xi@resolvent.net
License: AGPLv3 or Permissive for use with Open Source databases
Keywords: sql relational database query language
Platform: Any
